Metadata-Version: 1.2
Name: servifier
Version: 0.1.0
Summary: An easy-to-use tool for making web service with API from your own Python functions
Home-page: https://github.com/Nikolay-Lysenko/servifier
Author: Nikolay Lysenko
Author-email: nikolay-lysenco@yandex.ru
License: MIT
Keywords: web_service api_maker apify ml_engineering model_to_production
Platform: UNKNOWN
Requires-Python: >=3.6
